[
  {
    "ContainingType": "WebApplication1.Controllers.AuthenticationController",
    "Method": "Login",
    "RelativePath": "api/Authentication/login_post",
    "HttpMethod": "POST",
    "IsController": true,
    "Order": 0,
    "Parameters": [
      {
        "Name": "loginModel",
        "Type": "WebApplication1.Models.LoginModel",
        "IsRequired": true
      }
    ],
    "ReturnTypes": []
  },
  {
    "ContainingType": "WebApplication1.Controllers.ChatController",
    "Method": "GetAllChats",
    "RelativePath": "api/Chat/all-chats",
    "HttpMethod": "GET",
    "IsController": true,
    "Order": 0,
    "Parameters": [],
    "ReturnTypes": []
  },
  {
    "ContainingType": "WebApplication1.Controllers.ChatController",
    "Method": "GetAllPublicChats",
    "RelativePath": "api/Chat/all-public-chats",
    "HttpMethod": "GET",
    "IsController": true,
    "Order": 0,
    "Parameters": [],
    "ReturnTypes": []
  },
  {
    "ContainingType": "WebApplication1.Controllers.ChatController",
    "Method": "CreateDM",
    "RelativePath": "api/Chat/cerate-dm",
    "HttpMethod": "POST",
    "IsController": true,
    "Order": 0,
    "Parameters": [
      {
        "Name": "user_id",
        "Type": "System.Int32",
        "IsRequired": false
      },
      {
        "Name": "other_id",
        "Type": "System.Int32",
        "IsRequired": false
      }
    ],
    "ReturnTypes": []
  },
  {
    "ContainingType": "WebApplication1.Controllers.ChatController",
    "Method": "CreateGroupChat",
    "RelativePath": "api/Chat/create-group-chat",
    "HttpMethod": "POST",
    "IsController": true,
    "Order": 0,
    "Parameters": [
      {
        "Name": "creator_id",
        "Type": "System.Int32",
        "IsRequired": false
      },
      {
        "Name": "ids_string",
        "Type": "System.String",
        "IsRequired": false
      }
    ],
    "ReturnTypes": []
  },
  {
    "ContainingType": "WebApplication1.Controllers.ChatController",
    "Method": "CreatePublicChat",
    "RelativePath": "api/Chat/create-public-chat",
    "HttpMethod": "POST",
    "IsController": true,
    "Order": 0,
    "Parameters": [
      {
        "Name": "name",
        "Type": "System.String",
        "IsRequired": false
      },
      {
        "Name": "creator_id",
        "Type": "System.Int32",
        "IsRequired": false
      },
      {
        "Name": "desc",
        "Type": "System.String",
        "IsRequired": false
      }
    ],
    "ReturnTypes": []
  },
  {
    "ContainingType": "WebApplication1.Controllers.ChatController",
    "Method": "DeleteChat",
    "RelativePath": "api/Chat/delete-chat",
    "HttpMethod": "DELETE",
    "IsController": true,
    "Order": 0,
    "Parameters": [
      {
        "Name": "chat_id",
        "Type": "System.Int32",
        "IsRequired": false
      },
      {
        "Name": "user_id",
        "Type": "System.Int32",
        "IsRequired": false
      }
    ],
    "ReturnTypes": []
  },
  {
    "ContainingType": "WebApplication1.Controllers.ChatController",
    "Method": "EditChatDescription",
    "RelativePath": "api/Chat/edit-description",
    "HttpMethod": "PUT",
    "IsController": true,
    "Order": 0,
    "Parameters": [
      {
        "Name": "chatId",
        "Type": "System.Int32",
        "IsRequired": false
      },
      {
        "Name": "newChatDescription",
        "Type": "System.String",
        "IsRequired": false
      }
    ],
    "ReturnTypes": []
  },
  {
    "ContainingType": "WebApplication1.Controllers.ChatController",
    "Method": "EditChatName",
    "RelativePath": "api/Chat/edit-name",
    "HttpMethod": "PUT",
    "IsController": true,
    "Order": 0,
    "Parameters": [
      {
        "Name": "chatId",
        "Type": "System.Int32",
        "IsRequired": false
      },
      {
        "Name": "newChatName",
        "Type": "System.String",
        "IsRequired": false
      }
    ],
    "ReturnTypes": []
  },
  {
    "ContainingType": "WebApplication1.Controllers.ChatController",
    "Method": "GetChat",
    "RelativePath": "api/Chat/chat{id}",
    "HttpMethod": "GET",
    "IsController": true,
    "Order": 0,
    "Parameters": [
      {
        "Name": "id",
        "Type": "System.Int32",
        "IsRequired": true
      }
    ],
    "ReturnTypes": []
  },
  {
    "ContainingType": "WebApplication1.Controllers.MessageController",
    "Method": "EditMessageContent",
    "RelativePath": "api/Message/edit-message-content",
    "HttpMethod": "PUT",
    "IsController": true,
    "Order": 0,
    "Parameters": [
      {
        "Name": "message_id",
        "Type": "System.Int32",
        "IsRequired": false
      },
      {
        "Name": "user_id",
        "Type": "System.Int32",
        "IsRequired": false
      },
      {
        "Name": "new_content",
        "Type": "System.String",
        "IsRequired": false
      }
    ],
    "ReturnTypes": []
  },
  {
    "ContainingType": "WebApplication1.Controllers.MessageController",
    "Method": "GetMessages",
    "RelativePath": "api/Message/get-messages-from-chat{id}",
    "HttpMethod": "GET",
    "IsController": true,
    "Order": 0,
    "Parameters": [
      {
        "Name": "id",
        "Type": "System.Int32",
        "IsRequired": true
      }
    ],
    "ReturnTypes": []
  },
  {
    "ContainingType": "WebApplication1.Controllers.MessageController",
    "Method": "GetUserMessagesFromChat",
    "RelativePath": "api/Message/get-user-messages-in-chat",
    "HttpMethod": "GET",
    "IsController": true,
    "Order": 0,
    "Parameters": [
      {
        "Name": "user_id",
        "Type": "System.Int32",
        "IsRequired": false
      },
      {
        "Name": "chat_id",
        "Type": "System.Int32",
        "IsRequired": false
      }
    ],
    "ReturnTypes": []
  },
  {
    "ContainingType": "WebApplication1.Controllers.MessageController",
    "Method": "GetUserMessagesFromPublicChats",
    "RelativePath": "api/Message/get-user-messages-in-public-chats",
    "HttpMethod": "GET",
    "IsController": true,
    "Order": 0,
    "Parameters": [
      {
        "Name": "user_id",
        "Type": "System.Int32",
        "IsRequired": false
      }
    ],
    "ReturnTypes": []
  },
  {
    "ContainingType": "WebApplication1.Controllers.MessageController",
    "Method": "RemoveMessage",
    "RelativePath": "api/Message/remove-message",
    "HttpMethod": "DELETE",
    "IsController": true,
    "Order": 0,
    "Parameters": [
      {
        "Name": "message_id",
        "Type": "System.Int32",
        "IsRequired": false
      },
      {
        "Name": "user_id",
        "Type": "System.Int32",
        "IsRequired": false
      }
    ],
    "ReturnTypes": []
  },
  {
    "ContainingType": "WebApplication1.Controllers.MessageController",
    "Method": "SearchForMessage",
    "RelativePath": "api/Message/search-for-message",
    "HttpMethod": "GET",
    "IsController": true,
    "Order": 0,
    "Parameters": [
      {
        "Name": "search_prompt",
        "Type": "System.String",
        "IsRequired": false
      },
      {
        "Name": "chat_id",
        "Type": "System.Int32",
        "IsRequired": false
      }
    ],
    "ReturnTypes": []
  },
  {
    "ContainingType": "WebApplication1.Controllers.MessageController",
    "Method": "SendMessage",
    "RelativePath": "api/Message/send-message",
    "HttpMethod": "POST",
    "IsController": true,
    "Order": 0,
    "Parameters": [
      {
        "Name": "user_id",
        "Type": "System.Int32",
        "IsRequired": false
      },
      {
        "Name": "chat_id",
        "Type": "System.Int32",
        "IsRequired": false
      },
      {
        "Name": "content",
        "Type": "System.String",
        "IsRequired": false
      },
      {
        "Name": "reply_to",
        "Type": "System.Int32",
        "IsRequired": false
      }
    ],
    "ReturnTypes": []
  },
  {
    "ContainingType": "WebApplication1.Controllers.MessageInfoController",
    "Method": "MarkMessageAsSeen",
    "RelativePath": "api/MessageInfo/mark-as-seen",
    "HttpMethod": "PUT",
    "IsController": true,
    "Order": 0,
    "Parameters": [
      {
        "Name": "messageId",
        "Type": "System.Int32",
        "IsRequired": false
      }
    ],
    "ReturnTypes": []
  },
  {
    "ContainingType": "WebApplication1.Controllers.MessageUserReactionController",
    "Method": "AddReaction",
    "RelativePath": "api/MessageUserReaction/reaction-add",
    "HttpMethod": "POST",
    "IsController": true,
    "Order": 0,
    "Parameters": [
      {
        "Name": "reaction",
        "Type": "WebApplication1.Models.Message_User_Reaction",
        "IsRequired": true
      }
    ],
    "ReturnTypes": []
  },
  {
    "ContainingType": "WebApplication1.Controllers.MessageUserReactionController",
    "Method": "RemoveReaction",
    "RelativePath": "api/MessageUserReaction/reaction-remove",
    "HttpMethod": "DELETE",
    "IsController": true,
    "Order": 0,
    "Parameters": [
      {
        "Name": "reaction",
        "Type": "WebApplication1.Models.Message_User_Reaction",
        "IsRequired": true
      }
    ],
    "ReturnTypes": []
  },
  {
    "ContainingType": "WebApplication1.Controllers.ReportsController",
    "Method": "BanUser",
    "RelativePath": "api/Reports/ban-user",
    "HttpMethod": "PUT",
    "IsController": true,
    "Order": 0,
    "Parameters": [
      {
        "Name": "userId",
        "Type": "System.Int32",
        "IsRequired": false
      },
      {
        "Name": "banEnd",
        "Type": "System.DateTime",
        "IsRequired": false
      }
    ],
    "ReturnTypes": []
  },
  {
    "ContainingType": "WebApplication1.Controllers.ReportsController",
    "Method": "CreateReport",
    "RelativePath": "api/Reports/create-report",
    "HttpMethod": "POST",
    "IsController": true,
    "Order": 0,
    "Parameters": [
      {
        "Name": "report",
        "Type": "WebApplication1.Models.Report_Log",
        "IsRequired": true
      }
    ],
    "ReturnTypes": []
  },
  {
    "ContainingType": "WebApplication1.Controllers.ReportsController",
    "Method": "GetAll",
    "RelativePath": "api/Reports/get-all-reports",
    "HttpMethod": "GET",
    "IsController": true,
    "Order": 0,
    "Parameters": [],
    "ReturnTypes": []
  },
  {
    "ContainingType": "WebApplication1.Controllers.ReportsController",
    "Method": "GetAllUserId",
    "RelativePath": "api/Reports/get-all-reports-user-id",
    "HttpMethod": "GET",
    "IsController": true,
    "Order": 0,
    "Parameters": [
      {
        "Name": "Id",
        "Type": "System.Int32",
        "IsRequired": false
      }
    ],
    "ReturnTypes": []
  },
  {
    "ContainingType": "WebApplication1.Controllers.ReportsController",
    "Method": "IgnoreReport",
    "RelativePath": "api/Reports/ignore-report",
    "HttpMethod": "DELETE",
    "IsController": true,
    "Order": 0,
    "Parameters": [
      {
        "Name": "report",
        "Type": "WebApplication1.Models.Report_Log",
        "IsRequired": true
      }
    ],
    "ReturnTypes": []
  },
  {
    "ContainingType": "WebApplication1.Controllers.ReportsController",
    "Method": "GetAllUserReportsCount",
    "RelativePath": "api/Reports/reportsCount-AllUsers",
    "HttpMethod": "GET",
    "IsController": true,
    "Order": 0,
    "Parameters": [],
    "ReturnTypes": []
  },
  {
    "ContainingType": "WebApplication1.Controllers.ReportsController",
    "Method": "GetUserReportsCount",
    "RelativePath": "api/Reports/reportsCount-user{id}",
    "HttpMethod": "GET",
    "IsController": true,
    "Order": 0,
    "Parameters": [
      {
        "Name": "id",
        "Type": "System.Int32",
        "IsRequired": true
      }
    ],
    "ReturnTypes": []
  },
  {
    "ContainingType": "WebApplication1.Controllers.ReportsController",
    "Method": "TimeoutUser",
    "RelativePath": "api/Reports/timeout-user",
    "HttpMethod": "PUT",
    "IsController": true,
    "Order": 0,
    "Parameters": [
      {
        "Name": "userId",
        "Type": "System.Int32",
        "IsRequired": false
      },
      {
        "Name": "timeoutEnd",
        "Type": "System.DateTime",
        "IsRequired": false
      }
    ],
    "ReturnTypes": []
  },
  {
    "ContainingType": "WebApplication1.Controllers.UserController",
    "Method": "GetAllUsers",
    "RelativePath": "api/User/all-users",
    "HttpMethod": "GET",
    "IsController": true,
    "Order": 0,
    "Parameters": [],
    "ReturnTypes": []
  },
  {
    "ContainingType": "WebApplication1.Controllers.UserController",
    "Method": "GetBannedUsers",
    "RelativePath": "api/User/banned-users",
    "HttpMethod": "GET",
    "IsController": true,
    "Order": 0,
    "Parameters": [],
    "ReturnTypes": []
  },
  {
    "ContainingType": "WebApplication1.Controllers.UserController",
    "Method": "CreateUser",
    "RelativePath": "api/User/create-user",
    "HttpMethod": "POST",
    "IsController": true,
    "Order": 0,
    "Parameters": [
      {
        "Name": "user",
        "Type": "WebApplication1.Models.User",
        "IsRequired": true
      }
    ],
    "ReturnTypes": []
  },
  {
    "ContainingType": "WebApplication1.Controllers.UserController",
    "Method": "DeleteUser",
    "RelativePath": "api/User/delete-user",
    "HttpMethod": "DELETE",
    "IsController": true,
    "Order": 0,
    "Parameters": [
      {
        "Name": "user",
        "Type": "WebApplication1.Models.User",
        "IsRequired": true
      }
    ],
    "ReturnTypes": []
  },
  {
    "ContainingType": "WebApplication1.Controllers.UserController",
    "Method": "EditUser",
    "RelativePath": "api/User/edit-user{id}",
    "HttpMethod": "PUT",
    "IsController": true,
    "Order": 0,
    "Parameters": [
      {
        "Name": "id",
        "Type": "System.Int32",
        "IsRequired": true
      },
      {
        "Name": "user",
        "Type": "WebApplication1.Models.User",
        "IsRequired": true
      }
    ],
    "ReturnTypes": []
  },
  {
    "ContainingType": "WebApplication1.Controllers.UserController",
    "Method": "GetGoodUsers",
    "RelativePath": "api/User/good-users",
    "HttpMethod": "GET",
    "IsController": true,
    "Order": 0,
    "Parameters": [],
    "ReturnTypes": []
  },
  {
    "ContainingType": "WebApplication1.Controllers.UserController",
    "Method": "GetOnlineUsers",
    "RelativePath": "api/User/online",
    "HttpMethod": "GET",
    "IsController": true,
    "Order": 0,
    "Parameters": [],
    "ReturnTypes": []
  },
  {
    "ContainingType": "WebApplication1.Controllers.UserController",
    "Method": "GetTimeOutedUsers",
    "RelativePath": "api/User/timeouted-users",
    "HttpMethod": "GET",
    "IsController": true,
    "Order": 0,
    "Parameters": [],
    "ReturnTypes": []
  },
  {
    "ContainingType": "WebApplication1.Controllers.UserController",
    "Method": "GetUser",
    "RelativePath": "api/User/user{id}",
    "HttpMethod": "GET",
    "IsController": true,
    "Order": 0,
    "Parameters": [
      {
        "Name": "id",
        "Type": "System.Int32",
        "IsRequired": true
      }
    ],
    "ReturnTypes": []
  },
  {
    "ContainingType": "WebApplication1.Controllers.UserChatController",
    "Method": "CreateUserChat",
    "RelativePath": "api/UserChat/create-user-chat-link",
    "HttpMethod": "POST",
    "IsController": true,
    "Order": 0,
    "Parameters": [
      {
        "Name": "user_chat",
        "Type": "WebApplication1.Models.User_Chat",
        "IsRequired": true
      }
    ],
    "ReturnTypes": []
  },
  {
    "ContainingType": "WebApplication1.Controllers.UserChatController",
    "Method": "DeleteUserChat",
    "RelativePath": "api/UserChat/delete-user{userId}-chat{chatId}-link",
    "HttpMethod": "DELETE",
    "IsController": true,
    "Order": 0,
    "Parameters": [
      {
        "Name": "userId",
        "Type": "System.Int32",
        "IsRequired": true
      },
      {
        "Name": "chatId",
        "Type": "System.Int32",
        "IsRequired": true
      }
    ],
    "ReturnTypes": []
  },
  {
    "ContainingType": "WebApplication1.Controllers.UserChatController",
    "Method": "GetUsersLinks",
    "RelativePath": "api/UserChat/chat{id}-links",
    "HttpMethod": "GET",
    "IsController": true,
    "Order": 0,
    "Parameters": [
      {
        "Name": "id",
        "Type": "System.Int32",
        "IsRequired": true
      }
    ],
    "ReturnTypes": []
  },
  {
    "ContainingType": "WebApplication1.Controllers.UserChatController",
    "Method": "GetChatsOfUser",
    "RelativePath": "api/UserChat/chats-user{id}-is-in",
    "HttpMethod": "GET",
    "IsController": true,
    "Order": 0,
    "Parameters": [
      {
        "Name": "id",
        "Type": "System.Int32",
        "IsRequired": true
      }
    ],
    "ReturnTypes": []
  },
  {
    "ContainingType": "WebApplication1.Controllers.UserChatController",
    "Method": "GetUserInChat",
    "RelativePath": "api/UserChat/is-user{userId}-in-chat{chatId}",
    "HttpMethod": "GET",
    "IsController": true,
    "Order": 0,
    "Parameters": [
      {
        "Name": "userId",
        "Type": "System.Int32",
        "IsRequired": true
      },
      {
        "Name": "chatId",
        "Type": "System.Int32",
        "IsRequired": true
      }
    ],
    "ReturnTypes": []
  },
  {
    "ContainingType": "WebApplication1.Controllers.UserChatController",
    "Method": "GetPublicChatsOfUser",
    "RelativePath": "api/UserChat/public-chats-user{id}-is-in",
    "HttpMethod": "GET",
    "IsController": true,
    "Order": 0,
    "Parameters": [
      {
        "Name": "id",
        "Type": "System.Int32",
        "IsRequired": true
      }
    ],
    "ReturnTypes": []
  },
  {
    "ContainingType": "WebApplication1.Controllers.UserChatController",
    "Method": "GetUsersInChat",
    "RelativePath": "api/UserChat/users-in-chat{id}",
    "HttpMethod": "GET",
    "IsController": true,
    "Order": 0,
    "Parameters": [
      {
        "Name": "id",
        "Type": "System.Int32",
        "IsRequired": true
      }
    ],
    "ReturnTypes": []
  },
  {
    "ContainingType": "WebApplication1.Controllers.UserRelationshipController",
    "Method": "AcceptRequest",
    "RelativePath": "api/UserRelationship/accept-request-from{sender_id}-to{reciever_id}",
    "HttpMethod": "POST",
    "IsController": true,
    "Order": 0,
    "Parameters": [
      {
        "Name": "reciever_id",
        "Type": "System.Int32",
        "IsRequired": true
      },
      {
        "Name": "sender_id",
        "Type": "System.Int32",
        "IsRequired": true
      }
    ],
    "ReturnTypes": []
  },
  {
    "ContainingType": "WebApplication1.Controllers.UserRelationshipController",
    "Method": "GetBlockedUsers",
    "RelativePath": "api/UserRelationship/blocked-users-of-user{id}",
    "HttpMethod": "GET",
    "IsController": true,
    "Order": 0,
    "Parameters": [
      {
        "Name": "id",
        "Type": "System.Int32",
        "IsRequired": true
      }
    ],
    "ReturnTypes": []
  },
  {
    "ContainingType": "WebApplication1.Controllers.UserRelationshipController",
    "Method": "CancelRequest",
    "RelativePath": "api/UserRelationship/cancel-request-from{sender_id}-to{reciever_id}",
    "HttpMethod": "POST",
    "IsController": true,
    "Order": 0,
    "Parameters": [
      {
        "Name": "sender_id",
        "Type": "System.Int32",
        "IsRequired": true
      },
      {
        "Name": "reciever_id",
        "Type": "System.Int32",
        "IsRequired": true
      }
    ],
    "ReturnTypes": []
  },
  {
    "ContainingType": "WebApplication1.Controllers.UserRelationshipController",
    "Method": "GetFriends",
    "RelativePath": "api/UserRelationship/friends-of-user{id}",
    "HttpMethod": "GET",
    "IsController": true,
    "Order": 0,
    "Parameters": [
      {
        "Name": "id",
        "Type": "System.Int32",
        "IsRequired": true
      }
    ],
    "ReturnTypes": []
  },
  {
    "ContainingType": "WebApplication1.Controllers.UserRelationshipController",
    "Method": "GetAll",
    "RelativePath": "api/UserRelationship/get-all",
    "HttpMethod": "GET",
    "IsController": true,
    "Order": 0,
    "Parameters": [],
    "ReturnTypes": []
  },
  {
    "ContainingType": "WebApplication1.Controllers.UserRelationshipController",
    "Method": "GetRelationship",
    "RelativePath": "api/UserRelationship/get-relation",
    "HttpMethod": "GET",
    "IsController": true,
    "Order": 0,
    "Parameters": [
      {
        "Name": "id1",
        "Type": "System.Int32",
        "IsRequired": false
      },
      {
        "Name": "id2",
        "Type": "System.Int32",
        "IsRequired": false
      }
    ],
    "ReturnTypes": []
  },
  {
    "ContainingType": "WebApplication1.Controllers.UserRelationshipController",
    "Method": "ChangeNickname",
    "RelativePath": "api/UserRelationship/change-{user_id}-nickname-of-{friend_user_id}",
    "HttpMethod": "POST",
    "IsController": true,
    "Order": 0,
    "Parameters": [
      {
        "Name": "user_id",
        "Type": "System.Int32",
        "IsRequired": true
      },
      {
        "Name": "friend_user_id",
        "Type": "System.Int32",
        "IsRequired": true
      },
      {
        "Name": "nickname",
        "Type": "System.String",
        "IsRequired": false
      }
    ],
    "ReturnTypes": []
  },
  {
    "ContainingType": "WebApplication1.Controllers.UserRelationshipController",
    "Method": "GetMutedUsers",
    "RelativePath": "api/UserRelationship/muted-users-of-user{id}",
    "HttpMethod": "GET",
    "IsController": true,
    "Order": 0,
    "Parameters": [
      {
        "Name": "id",
        "Type": "System.Int32",
        "IsRequired": true
      }
    ],
    "ReturnTypes": []
  },
  {
    "ContainingType": "WebApplication1.Controllers.UserRelationshipController",
    "Method": "GetPendingRequestsOut",
    "RelativePath": "api/UserRelationship/pending-requests-from-user{id}",
    "HttpMethod": "GET",
    "IsController": true,
    "Order": 0,
    "Parameters": [
      {
        "Name": "id",
        "Type": "System.Int32",
        "IsRequired": true
      }
    ],
    "ReturnTypes": []
  },
  {
    "ContainingType": "WebApplication1.Controllers.UserRelationshipController",
    "Method": "GetPendingRequestsIn",
    "RelativePath": "api/UserRelationship/pending-requests-to-user{id}",
    "HttpMethod": "GET",
    "IsController": true,
    "Order": 0,
    "Parameters": [
      {
        "Name": "id",
        "Type": "System.Int32",
        "IsRequired": true
      }
    ],
    "ReturnTypes": []
  },
  {
    "ContainingType": "WebApplication1.Controllers.UserRelationshipController",
    "Method": "RejectRequest",
    "RelativePath": "api/UserRelationship/reject-request-from{sender_id}-to{reciever_id}",
    "HttpMethod": "POST",
    "IsController": true,
    "Order": 0,
    "Parameters": [
      {
        "Name": "reciever_id",
        "Type": "System.Int32",
        "IsRequired": true
      },
      {
        "Name": "sender_id",
        "Type": "System.Int32",
        "IsRequired": true
      }
    ],
    "ReturnTypes": []
  },
  {
    "ContainingType": "WebApplication1.Controllers.UserRelationshipController",
    "Method": "SendRequest",
    "RelativePath": "api/UserRelationship/send-request-from{sender_id}-to{reciever_id}",
    "HttpMethod": "POST",
    "IsController": true,
    "Order": 0,
    "Parameters": [
      {
        "Name": "sender_id",
        "Type": "System.Int32",
        "IsRequired": true
      },
      {
        "Name": "reciever_id",
        "Type": "System.Int32",
        "IsRequired": true
      }
    ],
    "ReturnTypes": []
  },
  {
    "ContainingType": "WebApplication1.Controllers.UserRelationshipController",
    "Method": "ToggleBlockUser",
    "RelativePath": "api/UserRelationship/toggle-{user_id}-block-{blocked_user_id}",
    "HttpMethod": "POST",
    "IsController": true,
    "Order": 0,
    "Parameters": [
      {
        "Name": "user_id",
        "Type": "System.Int32",
        "IsRequired": true
      },
      {
        "Name": "blocked_user_id",
        "Type": "System.Int32",
        "IsRequired": true
      }
    ],
    "ReturnTypes": []
  },
  {
    "ContainingType": "WebApplication1.Controllers.UserRelationshipController",
    "Method": "ToggleMuteUser",
    "RelativePath": "api/UserRelationship/toggle-{user_id}-mute-{muted_user_id}",
    "HttpMethod": "POST",
    "IsController": true,
    "Order": 0,
    "Parameters": [
      {
        "Name": "user_id",
        "Type": "System.Int32",
        "IsRequired": true
      },
      {
        "Name": "muted_user_id",
        "Type": "System.Int32",
        "IsRequired": true
      }
    ],
    "ReturnTypes": []
  },
  {
    "ContainingType": "WebApplication1.Controllers.UserRelationshipController",
    "Method": "UnfriendUser",
    "RelativePath": "api/UserRelationship/unfriend-{friend_user_id}-from-{user_id}",
    "HttpMethod": "POST",
    "IsController": true,
    "Order": 0,
    "Parameters": [
      {
        "Name": "user_id",
        "Type": "System.Int32",
        "IsRequired": true
      },
      {
        "Name": "friend_user_id",
        "Type": "System.Int32",
        "IsRequired": true
      }
    ],
    "ReturnTypes": []
  }
]